ipathy/__init__.py
ipathy/core.py
ipathy/ipathy.py
ipathy-0.1.3.dist-info/METADATA
ipathy-0.1.3.dist-info/WHEEL
ipathy-0.1.3.dist-info/license
ipathy-0.1.3.dist-info/top_level.txt
ipathy-0.1.3.dist-info/RECORD
