Metadata-Version: 2.1
Name: ipathy
Version: 0.1.3
Summary: The path fixer your OS forgot — cross-platform path normalizer for Python.
Author: PyBeast
Author-email: legendarycode111@gmail.com
License: MIT
Requires-Python: >=3.6
License-File: license
